siteflags/__init__.py
siteflags/admin.py
siteflags/apps.py
siteflags/models.py
siteflags/settings.py
siteflags/utils.py
siteflags/locale/en/LC_MESSAGES/django.po
siteflags/locale/ru/LC_MESSAGES/django.mo
siteflags/locale/ru/LC_MESSAGES/django.po
siteflags/migrations/0001_initial.py
siteflags/migrations/__init__.py
siteflags/tests/__init__.py
siteflags/tests/conftest.py
siteflags/tests/test_basic.py
siteflags/tests/testapp/__init__.py
siteflags/tests/testapp/models.py
django_siteflags-1.3.0.dist-info/AUTHORS
django_siteflags-1.3.0.dist-info/LICENSE
django_siteflags-1.3.0.dist-info/METADATA
django_siteflags-1.3.0.dist-info/WHEEL
django_siteflags-1.3.0.dist-info/top_level.txt
django_siteflags-1.3.0.dist-info/RECORD
